pertCF/Case.py
pertCF/Data.py
pertCF/PertCF.py
pertCF/Similarity.py
pertCF/__init__.py
pertCF-0.1.18.dist-info/LICENSE.txt
pertCF-0.1.18.dist-info/METADATA
pertCF-0.1.18.dist-info/WHEEL
pertCF-0.1.18.dist-info/top_level.txt
pertCF-0.1.18.dist-info/RECORD
